{
  "code": "0000",
  "message": "成功",
  "data": {
    "2073_10_115915": {
      "numFound": 4,
      "item": [
        {
          "school_id": "1359",
          "special_id": "1750646",
          "type": "2073",
          "batch": "10",
          "zslx": "-",
          "max": 0,
          "min": 423,
          "average": 0,
          "min_section": "106639",
          "lq_num": "-",
          "province": "35",
          "spe_id": "787",
          "info": "",
          "special_group": "115915",
          "first_km": "70000",
          "sp_type": "0",
          "sp_fxk": "",
          "sp_sxk": "",
          "sp_info": "",
          "sp_xuanke": "",
          "is_score_range": "2",
          "min_range": "",
          "min_rank_range": "",
          "remark": "",
          "level1_name": "专科(高职)",
          "level2_name": "电子与信息大类",
          "level3_name": "计算机类",
          "level1": "2",
          "level2": "25",
          "level3": "183",
          "spname": "软件技术",
          "sp_name": "软件技术",
          "zslx_name": "普通类",
          "local_batch_name": "专科批",
          "diff": 203,
          "sg_fxk": "70000",
          "sg_sxk": "70008",
          "sg_type": "80001",
          "sg_name": "8396（W999）",
          "sg_info": "首选物理，再选不限",
          "sg_xuanke": "70000_70001_70002^70000_70001_70003^70000_70001_70005^70000_70002_70003^70000_70002_70005^70000_70003_70005",
          "range_max_rank": "0"
        },
        {
          "school_id": "1359",
          "special_id": "1789402",
          "type": "2073",
          "batch": "10",
          "zslx": "-",
          "max": 0,
          "min": 418,
          "average": 0,
          "min_section": "109966",
          "lq_num": "-",
          "province": "35",
          "spe_id": "9161",
          "info": "",
          "special_group": "115915",
          "first_km": "70000",
          "sp_type": "0",
          "sp_fxk": "",
          "sp_sxk": "",
          "sp_info": "",
          "sp_xuanke": "",
          "is_score_range": "2",
          "min_range": "",
          "min_rank_range": "",
          "remark": null,
          "level1_name": "专科(高职)",
          "level2_name": "装备制造大类",
          "level3_name": "机械设计制造类",
          "level1": "2",
          "level2": "20",
          "level3": "157",
          "spname": "机械制造及自动化",
          "sp_name": "机械制造及自动化",
          "zslx_name": "普通类",
          "local_batch_name": "专科批",
          "diff": 198,
          "sg_fxk": "70000",
          "sg_sxk": "70008",
          "sg_type": "80001",
          "sg_name": "8396（W999）",
          "sg_info": "首选物理，再选不限",
          "sg_xuanke": "70000_70001_70002^70000_70001_70003^70000_70001_70005^70000_70002_70003^70000_70002_70005^70000_70003_70005",
          "range_max_rank": "0"
        },
        {
          "school_id": "1359",
          "special_id": "1789412",
          "type": "2073",
          "batch": "10",
          "zslx": "-",
          "max": 0,
          "min": 415,
          "average": 0,
          "min_section": "111922",
          "lq_num": "-",
          "province": "35",
          "spe_id": "595",
          "info": "",
          "special_group": "115915",
          "first_km": "70000",
          "sp_type": "0",
          "sp_fxk": "",
          "sp_sxk": "",
          "sp_info": "",
          "sp_xuanke": "",
          "is_score_range": "2",
          "min_range": "",
          "min_rank_range": "",
          "remark": null,
          "level1_name": "专科(高职)",
          "level2_name": "装备制造大类",
          "level3_name": "自动化类",
          "level1": "2",
          "level2": "20",
          "level3": "159",
          "spname": "智能控制技术",
          "sp_name": "智能控制技术",
          "zslx_name": "普通类",
          "local_batch_name": "专科批",
          "diff": 195,
          "sg_fxk": "70000",
          "sg_sxk": "70008",
          "sg_type": "80001",
          "sg_name": "8396（W999）",
          "sg_info": "首选物理，再选不限",
          "sg_xuanke": "70000_70001_70002^70000_70001_70003^70000_70001_70005^70000_70002_70003^70000_70002_70005^70000_70003_70005",
          "range_max_rank": "0"
        },
        {
          "school_id": "1359",
          "special_id": "1789396",
          "type": "2073",
          "batch": "10",
          "zslx": "-",
          "max": 0,
          "min": 410,
          "average": 0,
          "min_section": "115088",
          "lq_num": "-",
          "province": "35",
          "spe_id": "584",
          "info": "",
          "special_group": "115915",
          "first_km": "70000",
          "sp_type": "0",
          "sp_fxk": "",
          "sp_sxk": "",
          "sp_info": "",
          "sp_xuanke": "",
          "is_score_range": "2",
          "min_range": "",
          "min_rank_range": "",
          "remark": null,
          "level1_name": "专科(高职)",
          "level2_name": "装备制造大类",
          "level3_name": "机械设计制造类",
          "level1": "2",
          "level2": "20",
          "level3": "157",
          "spname": "工业工程技术",
          "sp_name": "工业工程技术",
          "zslx_name": "普通类",
          "local_batch_name": "专科批",
          "diff": 190,
          "sg_fxk": "70000",
          "sg_sxk": "70008",
          "sg_type": "80001",
          "sg_name": "8396（W999）",
          "sg_info": "首选物理，再选不限",
          "sg_xuanke": "70000_70001_70002^70000_70001_70003^70000_70001_70005^70000_70002_70003^70000_70002_70005^70000_70003_70005",
          "range_max_rank": "0"
        }
      ]
    },
    "2073_10_0": {
      "numFound": 4,
      "item": [
        {
          "school_id": "1359",
          "special_id": "1750646",
          "type": "2073",
          "batch": "10",
          "zslx": "-",
          "max": 0,
          "min": 423,
          "average": 0,
          "min_section": "106639",
          "lq_num": "-",
          "province": "35",
          "spe_id": "787",
          "info": "",
          "special_group": "115915",
          "first_km": "70000",
          "sp_type": "0",
          "sp_fxk": "",
          "sp_sxk": "",
          "sp_info": "",
          "sp_xuanke": "",
          "is_score_range": "2",
          "min_range": "",
          "min_rank_range": "",
          "remark": "",
          "level1_name": "专科(高职)",
          "level2_name": "电子与信息大类",
          "level3_name": "计算机类",
          "level1": "2",
          "level2": "25",
          "level3": "183",
          "spname": "软件技术",
          "sp_name": "软件技术",
          "zslx_name": "普通类",
          "local_batch_name": "专科批",
          "diff": 203,
          "sg_fxk": "70000",
          "sg_sxk": "70008",
          "sg_type": "80001",
          "sg_name": "8396（W999）",
          "sg_info": "首选物理，再选不限",
          "sg_xuanke": "70000_70001_70002^70000_70001_70003^70000_70001_70005^70000_70002_70003^70000_70002_70005^70000_70003_70005",
          "range_max_rank": "0"
        },
        {
          "school_id": "1359",
          "special_id": "1789402",
          "type": "2073",
          "batch": "10",
          "zslx": "-",
          "max": 0,
          "min": 418,
          "average": 0,
          "min_section": "109966",
          "lq_num": "-",
          "province": "35",
          "spe_id": "9161",
          "info": "",
          "special_group": "115915",
          "first_km": "70000",
          "sp_type": "0",
          "sp_fxk": "",
          "sp_sxk": "",
          "sp_info": "",
          "sp_xuanke": "",
          "is_score_range": "2",
          "min_range": "",
          "min_rank_range": "",
          "remark": null,
          "level1_name": "专科(高职)",
          "level2_name": "装备制造大类",
          "level3_name": "机械设计制造类",
          "level1": "2",
          "level2": "20",
          "level3": "157",
          "spname": "机械制造及自动化",
          "sp_name": "机械制造及自动化",
          "zslx_name": "普通类",
          "local_batch_name": "专科批",
          "diff": 198,
          "sg_fxk": "70000",
          "sg_sxk": "70008",
          "sg_type": "80001",
          "sg_name": "8396（W999）",
          "sg_info": "首选物理，再选不限",
          "sg_xuanke": "70000_70001_70002^70000_70001_70003^70000_70001_70005^70000_70002_70003^70000_70002_70005^70000_70003_70005",
          "range_max_rank": "0"
        },
        {
          "school_id": "1359",
          "special_id": "1789412",
          "type": "2073",
          "batch": "10",
          "zslx": "-",
          "max": 0,
          "min": 415,
          "average": 0,
          "min_section": "111922",
          "lq_num": "-",
          "province": "35",
          "spe_id": "595",
          "info": "",
          "special_group": "115915",
          "first_km": "70000",
          "sp_type": "0",
          "sp_fxk": "",
          "sp_sxk": "",
          "sp_info": "",
          "sp_xuanke": "",
          "is_score_range": "2",
          "min_range": "",
          "min_rank_range": "",
          "remark": null,
          "level1_name": "专科(高职)",
          "level2_name": "装备制造大类",
          "level3_name": "自动化类",
          "level1": "2",
          "level2": "20",
          "level3": "159",
          "spname": "智能控制技术",
          "sp_name": "智能控制技术",
          "zslx_name": "普通类",
          "local_batch_name": "专科批",
          "diff": 195,
          "sg_fxk": "70000",
          "sg_sxk": "70008",
          "sg_type": "80001",
          "sg_name": "8396（W999）",
          "sg_info": "首选物理，再选不限",
          "sg_xuanke": "70000_70001_70002^70000_70001_70003^70000_70001_70005^70000_70002_70003^70000_70002_70005^70000_70003_70005",
          "range_max_rank": "0"
        },
        {
          "school_id": "1359",
          "special_id": "1789396",
          "type": "2073",
          "batch": "10",
          "zslx": "-",
          "max": 0,
          "min": 410,
          "average": 0,
          "min_section": "115088",
          "lq_num": "-",
          "province": "35",
          "spe_id": "584",
          "info": "",
          "special_group": "115915",
          "first_km": "70000",
          "sp_type": "0",
          "sp_fxk": "",
          "sp_sxk": "",
          "sp_info": "",
          "sp_xuanke": "",
          "is_score_range": "2",
          "min_range": "",
          "min_rank_range": "",
          "remark": null,
          "level1_name": "专科(高职)",
          "level2_name": "装备制造大类",
          "level3_name": "机械设计制造类",
          "level1": "2",
          "level2": "20",
          "level3": "157",
          "spname": "工业工程技术",
          "sp_name": "工业工程技术",
          "zslx_name": "普通类",
          "local_batch_name": "专科批",
          "diff": 190,
          "sg_fxk": "70000",
          "sg_sxk": "70008",
          "sg_type": "80001",
          "sg_name": "8396（W999）",
          "sg_info": "首选物理，再选不限",
          "sg_xuanke": "70000_70001_70002^70000_70001_70003^70000_70001_70005^70000_70002_70003^70000_70002_70005^70000_70003_70005",
          "range_max_rank": "0"
        }
      ]
    }
  },
  "md5": "62c11bd17858a03f1ac0aac43d407dfb",
  "time": "2026-06-16 16:12:01"
}